<jpml id="SECTION-1story-PV-1highlight-white_template">
	<style src="GLOBAL-stylesheet.ejs" />
	<style src="SECTION-stylesheet.ejs" />
	<style src="PHONE-stylesheet.ejs" />
	<style>{
		#b1: {options: { $switch: [
				{if: =scale.phone, then: {PV_image:true}},
				{if: =portrait, then: {TH_image:{if: =scale.small, then:true, else:false}}},
				{if: =landscape, then: {TH-land_image:{if: =scale.small, then:true, else:false}}}			
			]}},
		#h4: { options: {single:true, white_highlight:true, indent:true, no_border:{if: =scale.phone, then:true, else:false}}}
		
	}</style>
	<style>{ 
		$switch: [
			{if: =scale.phone{
	
			}},
			{if: =portrait, then: {
				#b1:	{ frame: [0, 0, 768, 620]}
			}}, 
			{if: =landscape, then: {
				#b1:	{ frame: [0, 0, 768, 620]}
			}}
		]
	}</style>
	
	<box id="b1" embed="article" class="maude unit_deco" module="IMAGE-only_module.xml" />
	<box id="h4" embed="article" class="maude unit_highlight highlight_white" module="HIGHLIGHTS_module.xml" />
	<box id="ad_background_PV" class="maude unit_ad">
		<box id="highlight_ad" class="ad-rectangle" embed="advertisement" />
	</box>

	
</jpml>