<jpml id="SECTION-3story-G-deco-C_template">
	<style src="GLOBAL-stylesheet.ejs" />
	<style src="SECTION-stylesheet.ejs" />
	<style>{ 
		if: =portrait, then: {
			#b1:	{ 
						frame: {$switch: [
						{if: =scale.small, then: [0, 11, 571, 245]},
						{if: =scale.large, then: [0, 11, 571, 176]}
					]},
					options:{large_headline:true, no_border:true} 
			},
			#deco:	{ 
						frame: {$switch: [
						{if: =scale.small, then: [0, 257, 571, 362]},
						{if: =scale.large, then: [0, 188, 571, 432]}
					]},
					options:{normal_headline:true} 
			},
			#b2:	{ frame: [583, 11, 183, 314], options:{small_headline:true, no_border:true} },
			#b3:	{ frame: [583, 325, 183, 294], options:{small_headline:true} },
			#h1: {options:{highlight_dark:true}},
			#h2: {options:{highlight_dark:true}}
			
		}, else: {
			#b1:	{ frame: [11, 11, 571, 176], options:{large_headline:true, no_border:true} },
			#deco:	{ frame: [11, 188, 571, 432], options:{normal_headline:true} },
			#b2:	{ frame: [594, 11, 183, 316], options:{small_headline:true, no_border:true} },
			#b3:	{ frame: [594, 328, 183, 291], options:{small_headline:true} },
			#h1: {options:{highlight_dark:true}},
			#h2: {options:{highlight_dark:true}}
			
		}
	}</style>
	
	<box id="b1" embed="article" module="TOP-IMAGE_module.xml" />
	<box id="deco" embed="article" module="DECO_module.xml" />
	<box id="b2" embed="article" module="TOP-IMAGE_module.xml" />
	<box id="b3" embed="article" module="TOP-IMAGE_module.xml" />
	<box id="h1" embed="article" module="HIGHLIGHTS_module.xml" />
	<box id="h2" embed="article" module="HIGHLIGHTS_module.xml" />
	<box id="ad_background" class="ad_dark">
		<box id="highlight_ad" class="ad-rectangle" embed="advertisement" />
	</box>

	
</jpml>